hex_client
hex_client.py
hex_connection.py
setup.py
spellbook.py
HexClient.egg-info/PKG-INFO
HexClient.egg-info/SOURCES.txt
HexClient.egg-info/dependency_links.txt
HexClient.egg-info/requires.txt
HexClient.egg-info/top_level.txt