Metadata-Version: 1.0
Name: HexClient
Version: 0.1.2
Summary: A client for casting spells on the hex
Home-page: http://mrproctor.net
Author: Chris Proctor
Author-email: chris.proctor@gmail.com
License: MIT
Platform: UNKNOWN
